README.rst
setup.cfg
setup.py
scrapy_proxy_rotator/__init__.py
scrapy_proxy_rotator.egg-info/PKG-INFO
scrapy_proxy_rotator.egg-info/SOURCES.txt
scrapy_proxy_rotator.egg-info/dependency_links.txt
scrapy_proxy_rotator.egg-info/not-zip-safe
scrapy_proxy_rotator.egg-info/top_level.txt