Metadata-Version: 1.0
Name: scrapy-proxy-rotator
Version: 0.1.0
Summary: Scrapy downloader middleware that rotates proxies.
Home-page: https://github.com/povilasb/scrapy-proxy-rotator
Author: Povilas Balciunas
Author-email: balciunas90@gmail.com
License: MIT
Platform: UNKNOWN
